pytask_latex/__init__.py
pytask_latex/_version.py
pytask_latex/collect.py
pytask_latex/compilation_steps.py
pytask_latex/config.py
pytask_latex/execute.py
pytask_latex/plugin.py
pytask_latex/py.typed
pytask_latex/utils.py
pytask_latex-0.4.3.dist-info/METADATA
pytask_latex-0.4.3.dist-info/WHEEL
pytask_latex-0.4.3.dist-info/entry_points.txt
pytask_latex-0.4.3.dist-info/licenses/LICENSE
pytask_latex-0.4.3.dist-info/RECORD
