Metadata-Version: 2.4
Name: pytask_latex
Version: 0.4.3
Summary: Compile LaTeX documents with pytask.
Project-URL: Homepage, https://github.com/pytask-dev/pytask-latex
Project-URL: Changelog, https://github.com/pytask-dev/pytask-latex/blob/main/CHANGES.md
Project-URL: Documentation, https://github.com/pytask-dev/pytask-latex
Project-URL: Github, https://github.com/pytask-dev/pytask-latex
Project-URL: Tracker, https://github.com/pytask-dev/pytask-latex/issues
Author-email: Tobias Raabe <raabe@poste.de>
License: MIT
License-File: LICENSE
Classifier: Development Status :: 4 - Beta
Classifier: License :: OSI Approved :: MIT License
Classifier: Operating System :: OS Independent
Classifier: Programming Language :: Python :: 3
Classifier: Programming Language :: Python :: 3 :: Only
Requires-Python: >=3.9
Requires-Dist: latex-dependency-scanner>=0.1.3
Requires-Dist: pluggy>=1.0.0
Requires-Dist: pytask>=0.4.0
Provides-Extra: test
Requires-Dist: pytest; extra == 'test'
Requires-Dist: pytest-cov; extra == 'test'
Requires-Dist: pytest-xdist; extra == 'test'
Provides-Extra: typing
Requires-Dist: mypy>=1.10.0; extra == 'typing'
